docs/README_pypi.md
local_debug/test_dcm_problem.py
pathopatch/__init__.py
pathopatch/annotation_conversion.py
pathopatch/cli.py
pathopatch/macenko_vector_generation.py
pathopatch/wsi_extraction.py
pathopatch/base_ml/__init__.py
pathopatch/base_ml/base_cli.py
pathopatch/config/__init__.py
pathopatch/config/config.py
pathopatch/data/__init__.py
pathopatch/data/tissue_detector.pt
pathopatch/patch_extraction/__init__.py
pathopatch/patch_extraction/dataset.py
pathopatch/patch_extraction/patch_extraction.py
pathopatch/patch_extraction/process_batch.py
pathopatch/patch_extraction/storage.py
pathopatch/utils/__init__.py
pathopatch/utils/exceptions.py
pathopatch/utils/file_handling.py
pathopatch/utils/filters.py
pathopatch/utils/logger.py
pathopatch/utils/masking.py
pathopatch/utils/patch_dataset.py
pathopatch/utils/patch_util.py
pathopatch/utils/plotting.py
pathopatch/utils/tools.py
pathopatch/wsi_interfaces/__init__.py
pathopatch/wsi_interfaces/cucim_deepzoom.py
pathopatch/wsi_interfaces/openslide_deepzoom.py
pathopatch/wsi_interfaces/wsidicomizer_openslide.py
test_database/download.py
pathopatch-1.0.10.dist-info/METADATA
pathopatch-1.0.10.dist-info/WHEEL
pathopatch-1.0.10.dist-info/entry_points.txt
pathopatch-1.0.10.dist-info/top_level.txt
pathopatch-1.0.10.dist-info/RECORD
