Metadata-Version: 2.4
Name: pathopatch
Version: 1.0.10
Summary: PathoPatch - Accelerating Artificial Intelligence Based Whole Slide Image Analysis with an Optimized Preprocessing Pipeline
Author-email: Fabian Hörst <fabian.hoerst@uk-essen.de>
License: CC-BY-ND-4.0
Project-URL: Homepage, https://github.com/TIO-IKIM/PathoPatcher
Keywords: python,pathopatch
Classifier: Development Status :: 3 - Alpha
Classifier: Intended Audience :: Education
Classifier: Topic :: Scientific/Engineering :: Artificial Intelligence
Classifier: Programming Language :: Python :: 3
Classifier: Operating System :: MacOS :: MacOS X
Classifier: Operating System :: Microsoft :: Windows
Classifier: Operating System :: POSIX :: Other
Requires-Python: >=3.9
Requires-Dist: Pillow>=9.5.0
Requires-Dist: PyYAML
Requires-Dist: Shapely<=2.0.5,>=1.8.5.post1
Requires-Dist: colorama
Requires-Dist: future
Requires-Dist: geojson>=3.0.0
Requires-Dist: matplotlib
Requires-Dist: natsort
Requires-Dist: numpy<2.0.0
Requires-Dist: opencv_python_headless
Requires-Dist: openslide_python
Requires-Dist: pandas
Requires-Dist: pydantic<2.0,>=1.10.16
Requires-Dist: rasterio
Requires-Dist: requests
Requires-Dist: scikit-image<0.27
Requires-Dist: setuptools<=65.6.3
Requires-Dist: tqdm
Requires-Dist: torchvision
Requires-Dist: torch
Requires-Dist: wsidicom
Requires-Dist: wsidicomizer
Requires-Dist: pydicom==2.4.4
